{"copyright": "Copyright 2026 MLB Advanced Media, L.P.  Use of any content on this page acknowledges agreement to the terms posted here http://gdx.mlb.com/components/copyright.txt", "stats": [{"type": {"displayName": "season"}, "group": {"displayName": "pitching"}, "exemptions": [], "splits": [{"season": "2024", "stat": {"age": 29, "gamesPlayed": 16, "gamesStarted": 16, "groundOuts": 79, "airOuts": 78, "runs": 52, "doubles": 15, "triples": 2, "homeRuns": 16, "strikeOuts": 64, "baseOnBalls": 28, "intentionalWalks": 0, "hits": 89, "hitByPitch": 5, "avg": ".289", "atBats": 308, "obp": ".356", "slg": ".506", "ops": ".862", "caughtStealing": 2, "stolenBases": 12, "stolenBasePercentage": ".857", "caughtStealingPercentage": ".143", "groundIntoDoublePlay": 11, "numberOfPitches": 1336, "era": "5.38", "inningsPitched": "75.1", "wins": 1, "losses": 6, "saves": 0, "saveOpportunities": 0, "holds": 0, "blownSaves": 0, "earnedRuns": 45, "whip": "1.55", "battersFaced": 344, "outs": 226, "gamesPitched": 16, "completeGames": 0, "shutouts": 0, "strikes": 846, "strikePercentage": ".630", "hitBatsmen": 5, "balks": 0, "wildPitches": 3, "pickoffs": 0, "totalBases": 156, "groundOutsToAirouts": "1.01", "winPercentage": ".143", "pitchesPerInning": "17.73", "gamesFinished": 0, "strikeoutWalkRatio": "2.29", "strikeoutsPer9Inn": "7.65", "walksPer9Inn": "3.35", "hitsPer9Inn": "10.63", "runsScoredPer9": "6.21", "homeRunsPer9": "1.91", "inheritedRunners": 0, "inheritedRunnersScored": 0, "catchersInterference": 1, "sacBunts": 0, "sacFlies": 2}, "team": {"id": 119, "name": "Los Angeles Dodgers", "link": "/api/v1/teams/119"}, "player": {"id": 621111, "fullName": "Walker Buehler", "link": "/api/v1/people/621111"}, "league": {"id": 104, "name": "National League", "link": "/api/v1/league/104"}, "sport": {"id": 1, "link": "/api/v1/sports/1", "abbreviation": "MLB"}, "gameType": "R"}]}]}